metatypes/__init__.py
metatypes-0.1.3.dist-info/WHEEL
metatypes-0.1.3.dist-info/METADATA
metatypes-0.1.3.dist-info/RECORD
