Metadata-Version: 2.3
Name: metatypes
Version: 0.1.3
Summary: An Expressive Library for Static Typing
Author: Ilias Dzhabbarov
Author-email: Ilias Dzhabbarov <iliyas.dzabbarov@gmail.com>
License: MIT
Requires-Dist: ruff>=0.14.7
Requires-Python: >=3.14
Project-URL: Homepage, https://github.com/iliyasone/metatypes
Project-URL: Issues, https://github.com/iliyasone/metatypes/issues
